build/lib/typhon/__init__.py
build/lib/typhon/config.py
build/lib/typhon/constants.py
build/lib/typhon/environment.py
build/lib/typhon/geodesy.py
build/lib/typhon/geographical.py
build/lib/typhon/latex.py
build/lib/typhon/spectroscopy.py
build/lib/typhon/topography.py
build/lib/typhon/trees.py
build/lib/typhon/arts/__init__.py
build/lib/typhon/cloudmask/__init__.py
build/lib/typhon/cloudmask/aster.py
build/lib/typhon/cloudmask/cloudstatistics.py
build/lib/typhon/collocations/__init__.py
build/lib/typhon/collocations/collocator.py
build/lib/typhon/collocations/common.py
build/lib/typhon/datasets/__init__.py
build/lib/typhon/datasets/_tovs_defs.py
build/lib/typhon/datasets/dataset.py
build/lib/typhon/datasets/filters.py
build/lib/typhon/datasets/model.py
build/lib/typhon/datasets/tovs.py
build/lib/typhon/files/__init__.py
build/lib/typhon/files/fileset.py
build/lib/typhon/files/utils.py
build/lib/typhon/files/handlers/__init__.py
build/lib/typhon/files/handlers/cloudsat.py
build/lib/typhon/files/handlers/common.py
build/lib/typhon/files/handlers/hoaps.py
build/lib/typhon/files/handlers/meteosat.py
build/lib/typhon/files/handlers/ocean_rain.py
build/lib/typhon/files/handlers/satpy.py
build/lib/typhon/files/handlers/testers.py
build/lib/typhon/files/handlers/tovs.py
build/lib/typhon/files/handlers/tropomi.py
build/lib/typhon/math/__init__.py
build/lib/typhon/math/array.py
build/lib/typhon/math/common.py
build/lib/typhon/math/stats.py
build/lib/typhon/nonlte/__init__.py
build/lib/typhon/nonlte/const/__init__.py
build/lib/typhon/nonlte/mathmatics/__init__.py
build/lib/typhon/nonlte/nonltecalc/__init__.py
build/lib/typhon/nonlte/rtc/__init__.py
build/lib/typhon/nonlte/setup_atmosphere/__init__.py
build/lib/typhon/nonlte/spectra/__init__.py
build/lib/typhon/nonlte/spectra/abscoeff.py
build/lib/typhon/nonlte/spectra/lineshape.py
build/lib/typhon/nonlte/spectra/source_function.py
build/lib/typhon/physics/__init__.py
build/lib/typhon/physics/atmosphere.py
typhon-0.10.0.dist-info/LICENSE
typhon-0.10.0.dist-info/METADATA
typhon-0.10.0.dist-info/WHEEL
typhon-0.10.0.dist-info/top_level.txt
typhon-0.10.0.dist-info/RECORD
