Metadata-Version: 2.1
Name: typhon
Version: 0.10.0
Summary: Typhon is a collection of tools for atmospheric research.
Home-page: https://github.com/atmtools/typhon
Download-URL: https://github.com/atmtools/typhon/tarball/v0.10.0
Author: The Typhon developers
Author-email: The Typhon developers <typhon.mi@lists.uni-hamburg.de>
License: MIT License
Project-URL: Homepage, https://github.com/atmtools/typhon
Project-URL: Repository, https://github.com/atmtools/typhon
Project-URL: Issues, https://github.com/atmtools/typhon/issues
Keywords: one,two
Classifier: Development Status :: 4 - Beta
Classifier: Intended Audience :: Science/Research
Classifier: Topic :: Scientific/Engineering :: Atmospheric Science
Classifier: License :: OSI Approved :: MIT License
Classifier: Programming Language :: Python :: 3.10
Classifier: Programming Language :: Python :: 3.11
Classifier: Programming Language :: Python :: 3.12
Requires-Python: ~=3.10
License-File: LICENSE
Requires-Dist: docutils
Requires-Dist: fsspec !=2023.12.0,!=2023.12.1,!=2024.3.1
Requires-Dist: h5netcdf
Requires-Dist: imageio
Requires-Dist: matplotlib >=1.4
Requires-Dist: netCDF4 >=1.1.1
Requires-Dist: numexpr
Requires-Dist: numpy >=1.13
Requires-Dist: pandas
Requires-Dist: scikit-image
Requires-Dist: scikit-learn
Requires-Dist: scipy >=0.15.1
Requires-Dist: xarray >=0.10.2
Provides-Extra: docs
Requires-Dist: cartopy ; extra == 'docs'
Requires-Dist: pint ; extra == 'docs'
Requires-Dist: sphinx-rtd-theme ; extra == 'docs'
Provides-Extra: tests
Requires-Dist: pytest ; extra == 'tests'
Requires-Dist: pint ; extra == 'tests'
